db_modules/__init__.py
db_modules/mldata.py
db_modules-0.0.8.dist-info/METADATA
db_modules-0.0.8.dist-info/WHEEL
db_modules-0.0.8.dist-info/top_level.txt
db_modules-0.0.8.dist-info/RECORD
