Metadata-Version: 2.1
Name: db-modules
Version: 0.0.8
Summary: db_modules
Home-page: UNKNOWN
Author: Gabe Davis
Author-email: <youremail@email.com>
License: UNKNOWN
Keywords: python,first package
Platform: UNKNOWN
Classifier: Development Status :: 3 - Alpha
Classifier: Intended Audience :: Education
Classifier: Programming Language :: Python :: 2
Classifier: Programming Language :: Python :: 3
Classifier: Operating System :: MacOS :: MacOS X
Classifier: Operating System :: Microsoft :: Windows
